autoblock/__init__.py
autoblock/middleware.py
autoblock/utils.py
autoblock-1.3.0.dist-info/LICENSE
autoblock-1.3.0.dist-info/METADATA
autoblock-1.3.0.dist-info/WHEEL
autoblock-1.3.0.dist-info/top_level.txt
autoblock-1.3.0.dist-info/RECORD
